reloc/__init__.py
reloc/__version__.py
reloc/cli.py
reloc/client.py
reloc/server.py
reloc/util.py
reloc-0.0.6.dist-info/LICENSE
reloc-0.0.6.dist-info/METADATA
reloc-0.0.6.dist-info/WHEEL
reloc-0.0.6.dist-info/entry_points.txt
reloc-0.0.6.dist-info/top_level.txt
reloc-0.0.6.dist-info/RECORD
