Metadata-Version: 2.1
Name: reloc
Version: 0.0.6
Summary: A simple file transfer service
Home-page: https://github.com/normelius/reloc
Author: Anton Normelius
Author-email: a.normelius@gmail.com
License: UNKNOWN
Platform: UNKNOWN
Classifier: Programming Language :: Python :: 3
Classifier: License :: OSI Approved :: MIT License
Classifier: Operating System :: OS Independent
Requires-Python: >=3.6
Requires-Dist: backoff (==1.10.0)
Requires-Dist: certifi (==2020.4.5.2)
Requires-Dist: chardet (==3.0.4)
Requires-Dist: idna (==2.9)
Requires-Dist: ipify (==1.0.0)
Requires-Dist: requests (==2.23.0)
Requires-Dist: urllib3 (==1.25.9)
